{"cameraMode":{"drawMode":0,"name":"Shaded","section":"Shading Mode"},"sceneLighting":true,"audioPlay":false,"sceneViewState":{"showFog":false,"showMaterialUpdate":false,"showSkybox":false,"showFlares":false,"showImageEffects":false,"showParticleSystems":false,"showVisualEffectGraphs":true,"m_FxEnabled":true},"in2DMode":false,"pivot":{"x":1.4390709400177003,"y":-29.235105514526368,"z":-16.929096221923829},"rotation":{"x":-0.2209681123495102,"y":0.7702125310897827,"z":-0.3511657118797302,"w":-0.4845314025878906},"size":23.400053024291993,"orthographic":false}